{
	"healthbar_colors": [
		186,
		123,
		66
	],
	"position": [
		-300,
		-150
	],
	"scale": 1,
	"no_antialiasing": false,
	"camera_position": [
		0,
		0
	],
	"image": "characters/cablecrow",
	"sing_duration": 4,
	"healthicon": "cablecrow",
	"flip_x": false,
	"animations": [
		{
			"loop": true,
			"offsets": [
				0,
				0
			],
			"fps": 24,
			"anim": "idle",
			"indices": [],
			"name": "Idle"
		},
		{
			"loop": false,
			"offsets": [
				-11,
				2
			],
			"fps": 24,
			"anim": "singDOWN",
			"indices": [],
			"name": "Sing Down"
		},
		{
			"loop": false,
			"offsets": [
				-31,
				0
			],
			"anim": "singLEFT",
			"fps": 24,
			"name": "Sing Left"
		},
		{
			"loop": false,
			"offsets": [
				-157,
				-17
			],
			"fps": 24,
			"anim": "singRIGHT",
			"indices": [],
			"name": "Sing Right"
		},
		{
			"loop": false,
			"offsets": [
				-1,
				5
			],
			"fps": 24,
			"anim": "singUP",
			"indices": [],
			"name": "Sing Up"
		}
	]
}